klingon_file_manager/__init__.py
klingon_file_manager/delete.py
klingon_file_manager/get.py
klingon_file_manager/manage.py
klingon_file_manager/post.py
klingon_file_manager/utils.py
klingon_file_manager/tests/__init__.py
klingon_file_manager/tests/config.py
klingon_file_manager/tests/test_delete.py
klingon_file_manager/tests/test_functional_tests.py
klingon_file_manager/tests/test_get.py
klingon_file_manager/tests/test_move_file.py
klingon_file_manager/tests/test_post.py
klingon_file_manager/tests/test_utils_aws_credentials.py
klingon_file_manager/tests/test_utils_check_bucket_permissions.py
klingon_file_manager/tests/test_utils_get_mime_type.py
klingon_file_manager/tests/test_utils_md5.py
klingon_file_manager/tests/test_utils_parallel_check_bucket_permissions.py
tests/__init__.py
tests/config.py
tests/test_delete.py
tests/test_functional_tests.py
tests/test_get.py
tests/test_move_file.py
tests/test_post.py
tests/test_utils_aws_credentials.py
tests/test_utils_check_bucket_permissions.py
tests/test_utils_get_mime_type.py
tests/test_utils_md5.py
tests/test_utils_parallel_check_bucket_permissions.py
klingon_file_manager-0.0.36.dist-info/LICENSE
klingon_file_manager-0.0.36.dist-info/METADATA
klingon_file_manager-0.0.36.dist-info/WHEEL
klingon_file_manager-0.0.36.dist-info/entry_points.txt
klingon_file_manager-0.0.36.dist-info/top_level.txt
klingon_file_manager-0.0.36.dist-info/RECORD
