Metadata-Version: 2.1
Name: klingon_file_manager
Version: 0.0.36
Summary: A Python module for managing files on both local and AWS S3 storage.
Home-page: https://github.com/djh00t/module_klingon_file_manager
Author: David Hooton
Author-email: klingon_file_manager+david@hooton.org
Classifier: Programming Language :: Python :: 3
Classifier: License :: OSI Approved :: MIT License
Classifier: Operating System :: OS Independent
Requires-Python: >=3.6
License-File: LICENSE
Requires-Dist: boto3 >=1.18
Requires-Dist: pytest >=6.2
Requires-Dist: python-dotenv >=0.19
Requires-Dist: datetime
Requires-Dist: uuid
